tests/__init__.py
tests/test_pyencrypt.py
tests/test_pyfile.py
tests/test_pyimg.py
tests/test_pyspider.py
tests/test_pystr.py
tests/test_pytime.py
tests/test_pyurl.py
zxutils/__init__.py
zxutils/pyencrypt.py
zxutils/pyfile.py
zxutils/pyhttp.py
zxutils/pyimg.py
zxutils/pystr.py
zxutils/pytime.py
zxutils/pyurl.py
zxutils-1.0.2.dist-info/LICENSE
zxutils-1.0.2.dist-info/METADATA
zxutils-1.0.2.dist-info/WHEEL
zxutils-1.0.2.dist-info/top_level.txt
zxutils-1.0.2.dist-info/RECORD
