Metadata-Version: 2.1
Name: zxutils
Version: 1.0.2
Summary: python tool box
Home-page: https://github.com/zxyle/zxutils
Author: Zheng
Author-email: zxyful@gmail.com
License: MIT
Platform: UNKNOWN
